Metadata-Version: 1.0
Name: cxkParser
Version: 0.2.4
Summary: 用来给cxk处理数据
Home-page: UNKNOWN
Author: dxc
Author-email: dxclmrl@outlook.com
License: MIT Licence
Keywords: pip,cxkParser
Platform: any
